cogdl/__init__.py
cogdl/configs.py
cogdl/experiments.py
cogdl/options.py
cogdl/pipelines.py
cogdl/data/__init__.py
cogdl/data/batch.py
cogdl/data/data.py
cogdl/data/dataloader.py
cogdl/data/dataset.py
cogdl/data/sampler.py
cogdl/datasets/__init__.py
cogdl/datasets/customized_data.py
cogdl/datasets/gatne.py
cogdl/datasets/gcc_data.py
cogdl/datasets/geom_data.py
cogdl/datasets/grb_data.py
cogdl/datasets/gtn_data.py
cogdl/datasets/han_data.py
cogdl/datasets/kg_data.py
cogdl/datasets/matlab_matrix.py
cogdl/datasets/oagbert_data.py
cogdl/datasets/ogb.py
cogdl/datasets/planetoid_data.py
cogdl/datasets/rd2cd_data.py
cogdl/datasets/rec_data.py
cogdl/datasets/saint_data.py
cogdl/datasets/stgat_data.py
cogdl/datasets/stgcn_data.py
cogdl/datasets/tu_data.py
cogdl/layers/__init__.py
cogdl/layers/actgcn_layer.py
cogdl/layers/actgcnii_layer.py
cogdl/layers/actlinear_layer.py
cogdl/layers/actmlp_layer.py
cogdl/layers/actsage_layer.py
cogdl/layers/base_layer.py
cogdl/layers/deepergcn_layer.py
cogdl/layers/disengcn_layer.py
cogdl/layers/gat_layer.py
cogdl/layers/gat_layerii.py
cogdl/layers/gcn_layer.py
cogdl/layers/gcn_layerii.py
cogdl/layers/gcnii_layer.py
cogdl/layers/gin_layer.py
cogdl/layers/gine_layer.py
cogdl/layers/han_layer.py
cogdl/layers/mixhop_layer.py
cogdl/layers/mlp_layer.py
cogdl/layers/pprgo_layer.py
cogdl/layers/reversible_layer.py
cogdl/layers/rgcn_layer.py
cogdl/layers/sage_layer.py
cogdl/layers/saint_layer.py
cogdl/layers/se_layer.py
cogdl/layers/set2set.py
cogdl/layers/sgc_layer.py
cogdl/layers/stgat_layer.py
cogdl/layers/stgcn_layer.py
cogdl/layers/jittor/__init__.py
cogdl/layers/jittor/gcn_layer.py
cogdl/loggers/__init__.py
cogdl/loggers/base_logger.py
cogdl/loggers/tensorboard_logger.py
cogdl/loggers/wandb_logger.py
cogdl/models/__init__.py
cogdl/models/base_model.py
cogdl/models/emb/__init__.py
cogdl/models/emb/complex.py
cogdl/models/emb/deepwalk.py
cogdl/models/emb/dgk.py
cogdl/models/emb/distmult.py
cogdl/models/emb/dngr.py
cogdl/models/emb/gatne.py
cogdl-0.6.dist-info/LICENSE
cogdl-0.6.dist-info/METADATA
cogdl-0.6.dist-info/WHEEL
cogdl-0.6.dist-info/top_level.txt
cogdl-0.6.dist-info/RECORD
