Metadata-Version: 2.1
Name: cogdl
Version: 0.6
Summary: An Extensive Research Toolkit for Deep Learning on Graphs
Home-page: https://github.com/THUDM/cogdl
License: MIT
Keywords: network embedding,graph representation learning,graph neural networks
Classifier: Development Status :: 3 - Alpha
Classifier: Intended Audience :: Science/Research
Classifier: Intended Audience :: Developers
Classifier: Topic :: Scientific/Engineering :: Artificial Intelligence
Classifier: License :: OSI Approved :: MIT License
Classifier: Programming Language :: Python :: 3
Classifier: Programming Language :: Python :: 3.6
Classifier: Programming Language :: Python :: 3.7
Classifier: Programming Language :: Python :: 3.8
Classifier: Programming Language :: Python :: 3.9
Classifier: Programming Language :: Python :: 3.10
License-File: LICENSE
Requires-Dist: torch
Requires-Dist: importlib-metadata (<5.0)
Requires-Dist: networkx
Requires-Dist: matplotlib
Requires-Dist: tqdm
Requires-Dist: numpy (>=1.21)
Requires-Dist: scipy
Requires-Dist: gensim (>=4.0)
Requires-Dist: grave
Requires-Dist: scikit-learn
Requires-Dist: tabulate
Requires-Dist: optuna (==2.4.0)
Requires-Dist: ogb
Requires-Dist: pre-commit
Requires-Dist: flake8
Requires-Dist: numba
Requires-Dist: ninja
Requires-Dist: transformers
Requires-Dist: sentencepiece
